Juliustools/Juliustools.py
Juliustools/__init__.py
juliustools-0.1.1.dist-info/LICENSE
juliustools-0.1.1.dist-info/METADATA
juliustools-0.1.1.dist-info/WHEEL
juliustools-0.1.1.dist-info/top_level.txt
juliustools-0.1.1.dist-info/RECORD
