Metadata-Version: 2.1
Name: juliustools
Version: 0.1.1
Summary: An API wrapper for the Julius Tools API
Author: julianwe17
License: MIT
Project-URL: GitHub, https://github.com/Julianwe17/juliustools
Project-URL: Julius, https://juliusbot.eu/
Keywords: julius,tools,api,wrapper
Classifier: Development Status :: 4 - Beta
Classifier: License :: OSI Approved :: MIT License
Classifier: Operating System :: OS Independent
Classifier: Intended Audience :: Developers
Classifier: Programming Language :: Python :: 3.9
Classifier: Programming Language :: Python :: 3.10
Classifier: Programming Language :: Python :: 3.11
Classifier: Programming Language :: Python :: 3.12
Requires-Python: >=3.9
License-File: LICENSE
Requires-Dist: requests
Requires-Dist: aiohttp
